[
  {
    "label": "Serverless",
    "data": {
      "text": "Serverless code runs on which of the following?",
      "options": [
        {
          "text": "Potatoes",
          "value": "potatoes"
        },
        {
          "text": "Servers",
          "value": "servers"
        },
        {
          "text": "Hope",
          "value": "hope"
        },
        {
          "text": "Developer Tears",
          "value": "developer-tears"
        }
      ],
      "answer": "servers"
    }
  },
  {
    "label": "AWS",
    "data": {
      "text": "AWS Stands for which of the following?",
      "options": [
        {
          "text": "Amazon Web Systems",
          "value": "amazon-web-systems"
        },
        {
          "text": "Amazon Web Services",
          "value": "amazon-web-services"
        },
        {
          "text": "AWSome Sauce",
          "value": "awesome-sauce"
        }
      ],
      "answer": "amazon-web-services"
    }
  },
  {
    "label": "Database",
    "data": {
      "text": "Which AWS service provides a fully managed NoSQL database?",
      "options": [
        {
          "text": "RDS",
          "value": "rds"
        },
        {
          "text": "DynamoDB",
          "value": "dynamodb"
        },
        {
          "text": "Redshift",
          "value": "redshift"
        },
        {
          "text": "CloudFront",
          "value": "cloudfront"
        }
      ],
      "answer": "dynamodb"
    }
  },
  {
    "label": "Celebrity",
    "data": {
      "text": "Which celebrity may have given a quote on SST?",
      "options": [
        {
          "text": "Rosalind Franklin",
          "value": "franklin"
        },
        {
          "text": "Mark Twain",
          "value": "twain"
        },
        {
          "text": "Taylor Swift",
          "value": "swift"
        },
        {
          "text": "Danny DeVito",
          "value": "devito"
        }
      ],
      "answer": "swift"
    }
  },
  {
    "label": "Meaning of Life",
    "data": {
      "text": "What is the meaning of life, the universe and everything?",
      "options": [
        {
          "text": "42",
          "value": "forty-two"
        },
        {
          "text": "Taco Tuesday",
          "value": "taco-tuesday"
        },
        {
          "text": "The ShamWow",
          "value": "shamwow"
        },
        {
          "text": "DS9 S1E10",
          "value": "ds9"
        }
      ],
      "answer": "forty-two"
    }
  },
  {
    "label": "CHUD",
    "data": {
      "text": "In the 1984 movie C.H.U.D, what does C.H.U.D stand for?",
      "options": [
        {
          "text": "Canned Ham Under Duress",
          "value": "ham"
        },
        {
          "text": "Control Humans Using Drugs",
          "value": "drugs"
        },
        {
          "text": "Cannibalistic Humanoid Underground Dwellers",
          "value": "cannibalistic"
        },
        {
          "text": "Canadian Hillbilly Unstoppable Demons",
          "value": "demons"
        }
      ],
      "answer": "cannibalistic"
    }
  }
]
